narg2p_cli/eval_lm.py
narg2p_cli/preprocess.py
narg2p_cli/hydra_train.py
narg2p_cli/interactive.py
narg2p_cli/score.py
narg2p_cli/train.py
narg2p_cli/__init__.py
narg2p_cli/generate.py
narg2p_cli/validate.py
narg2p-0.1.3.dist-info/top_level.txt
narg2p-0.1.3.dist-info/entry_points.txt
narg2p-0.1.3.dist-info/WHEEL
narg2p-0.1.3.dist-info/METADATA
narg2p-0.1.3.dist-info/RECORD
narg2p/sequence_scorer.py
narg2p/nan_detector.py
narg2p/libbleu.cpython-310-x86_64-linux-gnu.so
narg2p/search.py
narg2p/pdb.py
narg2p/token_generation_constraints.py
narg2p/iterative_refinement_generator.py
narg2p/incremental_decoding_utils.py
narg2p/binarizer.py
narg2p/sequence_generator.py
narg2p/__init__.py
narg2p/trainer.py
narg2p/hub_utils.py
narg2p/quantization_utils.py
narg2p/options.py
narg2p/file_io.py
narg2p/file_utils.py
narg2p/ngram_repeat_block.py
narg2p/checkpoint_utils.py
narg2p/utils.py
narg2p/registry.py
narg2p/libnat.cpython-310-x86_64-linux-gnu.so
narg2p/version.py
narg2p/tokenizer.py
narg2p/model_parallel/megatron_trainer.py
narg2p/model_parallel/__init__.py
narg2p/model_parallel/criterions/vocab_parallel_cross_entropy.py
narg2p/model_parallel/criterions/__init__.py
narg2p/model_parallel/modules/__init__.py
narg2p/model_parallel/modules/transformer_layer.py
narg2p/model_parallel/modules/multihead_attention.py
narg2p/model_parallel/models/transformer_lm.py
narg2p/model_parallel/models/transformer.py
narg2p/model_parallel/models/__init__.py
narg2p/model_parallel/models/pipeline_parallel_transformer/model.py
narg2p/model_parallel/models/pipeline_parallel_transformer/layers.py
narg2p/model_parallel/models/pipeline_parallel_transformer/__init__.py
narg2p/model_parallel/models/roberta/model.py
narg2p/model_parallel/models/roberta/__init__.py
narg2p/optim/cpu_adam.py
narg2p/optim/composite.py
narg2p/optim/fused_adam.py
narg2p/optim/shard.py
narg2p/optim/fp16_optimizer.py
narg2p/optim/adadelta.py
narg2p/optim/sgd.py
narg2p/optim/dynamic_loss_scaler.py
narg2p/optim/bmuf.py
narg2p/optim/adamax.py
narg2p/optim/narg2p_optimizer.py
narg2p/optim/adam.py
narg2p/optim/__init__.py
