Metadata-Version: 2.1
Name: narg2p
Version: 0.1.3
Summary: Non AutoRegressive Grapheme to Phoneme conversion Toolkit
Home-page: https://github.com/pytorch/narg2p
Classifier: Intended Audience :: Science/Research
Classifier: License :: OSI Approved :: MIT License
Classifier: Programming Language :: Python :: 3.6
Classifier: Programming Language :: Python :: 3.7
Classifier: Programming Language :: Python :: 3.8
Classifier: Topic :: Scientific/Engineering :: Artificial Intelligence
Requires-Dist: cffi
Requires-Dist: cython
Requires-Dist: hydra-core (<1.1)
Requires-Dist: omegaconf (<2.1)
Requires-Dist: regex
Requires-Dist: sacrebleu (>=1.4.12)
Requires-Dist: torch
Requires-Dist: tqdm
Requires-Dist: dataclasses ; python_version < "3.7"
Requires-Dist: numpy (<1.20.0) ; python_version < "3.7"
Requires-Dist: numpy ; python_version >= "3.7"
